pyboleto/__init__.py
pyboleto/data.py
pyboleto/html.py
pyboleto/pdf.py
pyboleto/bank/__init__.py
pyboleto/bank/bancodobrasil.py
pyboleto/bank/banrisul.py
pyboleto/bank/bradesco.py
pyboleto/bank/caixa.py
pyboleto/bank/caixa_sigcb.py
pyboleto/bank/cecred.py
pyboleto/bank/hsbc.py
pyboleto/bank/itau.py
pyboleto/bank/real.py
pyboleto/bank/santander.py
pyboleto/bank/sicoob.py
pyboleto/bank/sicredi.py
pyboleto/django/__init__.py
pyboleto/django/admin.py
pyboleto/django/models.py
pyboleto/django/views.py
pyboleto/media/logo_bancobradesco.jpg
pyboleto/media/logo_bancocaixa.jpg
pyboleto/media/logo_bancohsbc.jpg
pyboleto/media/logo_bancoreal.jpg
pyboleto/media/logo_banrisul.jpg
pyboleto/media/logo_bb.jpg
pyboleto/media/logo_cecred.jpg
pyboleto/media/logo_itau.jpg
pyboleto/media/logo_santander.png
pyboleto/media/logo_sicoob.jpg
pyboleto/media/logo_sicredi.jpg
pyboleto/templates/head.html
pyboleto/templates/recibo_caixa.html
pyboleto/templates/recibo_sacado.html
python_boleto-0.3.6.data/scripts/html_pyboleto_sample.py
python_boleto-0.3.6.data/scripts/pdf_pyboleto_sample.py
python_boleto-0.3.6.dist-info/DESCRIPTION.rst
python_boleto-0.3.6.dist-info/METADATA
python_boleto-0.3.6.dist-info/RECORD
python_boleto-0.3.6.dist-info/WHEEL
python_boleto-0.3.6.dist-info/metadata.json
python_boleto-0.3.6.dist-info/top_level.txt
tests/__init__.py
tests/alltests.py
tests/test_banco_banrisul.py
tests/test_banco_bradesco.py
tests/test_banco_caixa.py
tests/test_banco_do_brasil.py
tests/test_banco_hsbc.py
tests/test_banco_hsbc_com_registro.py
tests/test_banco_itau.py
tests/test_banco_real.py
tests/test_banco_santander.py
tests/test_banco_sicoob.py
tests/testutils.py
tests/xml/BoletoBB-expected.xml
tests/xml/BoletoBanrisul-expected.xml
tests/xml/BoletoBradesco-expected.xml
tests/xml/BoletoCaixa-expected.xml
tests/xml/BoletoHsbc-expected.xml
tests/xml/BoletoHsbcComRegistro-expected.xml
tests/xml/BoletoItau-expected.xml
tests/xml/BoletoReal-expected.xml
tests/xml/BoletoSantander-expected.xml
tests/xml/Triplo-BoletoBB-expected.xml
tests/xml/Triplo-BoletoBanrisul-expected.xml
tests/xml/Triplo-BoletoBradesco-expected.xml
tests/xml/Triplo-BoletoCaixa-expected.xml
