Metadata-Version: 2.0
Name: python-boleto
Version: 0.3.6
Summary: Python Library to create "boletos de cobrança bancária" for     several Brazilian banks
Home-page: https://github.com/Trust-Code/python-boleto
Author: Trust-Code
Author-email: suporte@trustcode.com.br
License: BSD
Download-URL: http://pypi.python.org/pypi/pyboleto
Platform: any
Classifier: Development Status :: 4 - Beta
Classifier: Operating System :: OS Independent
Classifier: Intended Audience :: Developers
Classifier: Intended Audience :: Financial and Insurance Industry
Classifier: Operating System :: OS Independent
Classifier: License :: OSI Approved :: BSD License
Classifier: Natural Language :: Portuguese (Brazilian)
Classifier: Programming Language :: Python
Classifier: Programming Language :: Python :: 3
Classifier: Programming Language :: Python :: 2.7
Classifier: Programming Language :: Python :: 2.6
Classifier: Topic :: Office/Business :: Financial
Classifier: Topic :: Software Development :: Libraries :: Python Modules
Classifier: Framework :: Django
Provides: pyboleto
Requires-Dist: reportlab
